images/rpki-cert-detail.png
images/rpki-certasn-detail.png
images/rpki-certprefix-detail.png
images/rpki-org-detail.png
images/rpki-roa-detail.png
images/rpki-roaprefix-detail.png
netbox_rpki/__init__.py
netbox_rpki/choices.py
netbox_rpki/filtersets.py
netbox_rpki/forms.py
netbox_rpki/models.py
netbox_rpki/navigation.py
netbox_rpki/netbox_rpki.code-workspace
netbox_rpki/tables.py
netbox_rpki/urls.py
netbox_rpki/version.py
netbox_rpki/views.py
netbox_rpki/api/__init__.py
netbox_rpki/api/serializers.py
netbox_rpki/api/urls.py
netbox_rpki/api/views.py
netbox_rpki/graphql/__init__.py
netbox_rpki/graphql/filters.py
netbox_rpki/graphql/schema.py
netbox_rpki/graphql/types.py
netbox_rpki/migrations/00005_rpki.py
netbox_rpki/migrations/0001_initial.py
netbox_rpki/migrations/0002__add_tenancy.py
netbox_rpki/migrations/0003_add_comments_fields.py
netbox_rpki/migrations/0004_assignedresources.py
netbox_rpki/migrations/__init__.py
netbox_rpki/templates/netbox_rpki/certificate.html
netbox_rpki/templates/netbox_rpki/certificateasn.html
netbox_rpki/templates/netbox_rpki/certificateprefix.html
netbox_rpki/templates/netbox_rpki/organization.html
netbox_rpki/templates/netbox_rpki/roa.html
netbox_rpki/templates/netbox_rpki/roaprefix.html
netbox_rpki/tests/__init__.py
netbox_rpki/tests/test_api.py
netbox_rpki/tests/test_forms.py
netbox_rpki-0.1.5.dist-info/LICENSE
netbox_rpki-0.1.5.dist-info/METADATA
netbox_rpki-0.1.5.dist-info/WHEEL
netbox_rpki-0.1.5.dist-info/top_level.txt
netbox_rpki-0.1.5.dist-info/RECORD
