Metadata-Version: 2.2
Name: netbox_rpki
Version: 0.1.5
Summary: NetBox plugin for BGP RPKI support.
Author-email: Mencken Davidson <mencken@gmail.com>
Maintainer-email: Mencken Davidson <mencken@gmail.com>
License: 
Project-URL: Documentation, https://github.com/menckend/netbox_rpki/blob/main/README.md
Project-URL: Source, https://github.com/menckend/netbox_rpki
Project-URL: Tracker, https://github.com/menckend/netbox_rpki/issues
Keywords: netbox,plugin,bgp,rpki,roa
Classifier: Development Status :: 3 - Alpha
Classifier: Intended Audience :: Developers
Classifier: Natural Language :: English
Classifier: Programming Language :: Python :: 3 :: Only
Classifier: Programming Language :: Python :: 3.6
Classifier: Programming Language :: Python :: 3.10
Classifier: Programming Language :: Python :: 3.11
Classifier: Programming Language :: Python :: 3.12
Requires-Python: >=3.6.8
License-File: LICENSE
Requires-Dist: build
Provides-Extra: test
Requires-Dist: black==24.3.0; extra == "test"
Requires-Dist: check-manifest==0.49; extra == "test"
Requires-Dist: flake8; extra == "test"
Requires-Dist: flake8-pyproject; extra == "test"
Requires-Dist: pre-commit==3.7.0; extra == "test"
Requires-Dist: pytest==8.1.1; extra == "test"
